SimpleTopicModel/SimpleTopicModel.py
SimpleTopicModel/__init__.py
SimpleTopicModel-0.0.7.dist-info/LICENSE
SimpleTopicModel-0.0.7.dist-info/METADATA
SimpleTopicModel-0.0.7.dist-info/WHEEL
SimpleTopicModel-0.0.7.dist-info/top_level.txt
SimpleTopicModel-0.0.7.dist-info/RECORD
