Metadata-Version: 2.1
Name: SimpleTopicModel
Version: 0.0.7
Summary: An NLP Package for generating Topic Models
Home-page: UNKNOWN
Author: decafsunrise
Author-email: alembichosting@gmail.com
License: UNKNOWN
Project-URL: GitHub, https://github.com/DecafSunrise/SimpleTopicModel
Platform: UNKNOWN
Requires-Dist: hdbscan (==0.8.33)
Requires-Dist: pandas (==1.5.1)
Requires-Dist: plotly (==5.11.0)
Requires-Dist: sentence-transformers (==2.2.2)
Requires-Dist: setuptools (==49.2.1)
Requires-Dist: tqdm (==4.65.0)
Requires-Dist: umap (==0.1.1)
